Metadata-Version: 2.1
Name: prometheus-connect
Version: 0.0.1
Summary: A small python api to collect data from prometheus
Home-page: https://github.com/4n4nd/prometheus-connect
Author: Anand Sanmukhani
Author-email: asan@bu.edu
License: UNKNOWN
Platform: UNKNOWN
Classifier: Programming Language :: Python :: 3.6
Classifier: License :: OSI Approved :: MIT License
Classifier: Operating System :: OS Independent
